d_heap
