Metadata-Version: 1.1
Name: d-heap
Version: 0.0.2
Summary: Python functions for working with D-ary Heap (Heap with more than 2 child nodes)
Home-page: https://github.com/rameshrvr/d-ary_heap
Author: Ramesh RV
Author-email: rameshrvr@outlook.com
License: MIT License
Keywords: d-heap heap python-heap min-heap max-heap
Platform: All
Classifier: Programming Language :: Python :: 2.7
Classifier: Programming Language :: Python :: 3.5
Classifier: Programming Language :: Python :: 3.6
Classifier: Programming Language :: Python :: 3.7
